{
  "type": "FeatureCollection",
  "name": "servicios_salud",
  "features": [{
      "type": "Feature",
      "properties": {
        "CodSS": "6.000000",
        "NomSS": "SS Valpo San Antonio",
        "CodReg": "5.000000",
        "NomReg": "De Valparaíso",
        "CodCom": "5101.000000",
        "NomCom": "Valparaíso",
        "TipoEst": "Dirección Servicio de Salud",
        "ViaAcceso": "Avenida",
        "Direcc": "Brasil 1435 Valparaiso",
        "Fono": "S\/N",
        "CoordX19": "255236.160000",
        "CoordY19": "6340748.520000"
      },
      "geometry": {
        "type": "Point",
        "coordinates": [-71.621091, -33.044294]
      }
    }

  ]
}
